shrillerspot/__init__.py
shrillerspot/auth/__init__.py
shrillerspot/auth/auth.py
shrillerspot/playlist/__init__.py
shrillerspot/playlist/fetch_playlist.py
shrillerspot/user/__init__.py
shrillerspot/user/saved_tracks.py
shrillerspot/utility/__init__.py
shrillerspot-1.2.dist-info/METADATA
shrillerspot-1.2.dist-info/WHEEL
shrillerspot-1.2.dist-info/top_level.txt
shrillerspot-1.2.dist-info/RECORD
