Metadata-Version: 2.1
Name: shrillerspot
Version: 1.2
Summary: Your description of the project
Author: shriller44
Author-email: shriller@gmail.com
Classifier: Programming Language :: Python :: 3
Classifier: Operating System :: OS Independent
